{
  "routes": [
    {
      "method": "GET",
      "path": "/capes",
      "handler": "cape.find",
      "config": {
        "policies": []
      }
    },
    {
      "method": "GET",
      "path": "/capes/count",
      "handler": "cape.count",
      "config": {
        "policies": []
      }
    },
    {
      "method": "GET",
      "path": "/capes/:id",
      "handler": "cape.findOne",
      "config": {
        "policies": []
      }
    },
    {
      "method": "POST",
      "path": "/capes",
      "handler": "cape.create",
      "config": {
        "policies": []
      }
    },
    {
      "method": "PUT",
      "path": "/capes/:id",
      "handler": "cape.update",
      "config": {
        "policies": []
      }
    },
    {
      "method": "DELETE",
      "path": "/capes/:id",
      "handler": "cape.delete",
      "config": {
        "policies": []
      }
    }
  ]
}
